psd2html/__init__.py
psd2html/__main__.py
psd2html/io.py
psd2html/logger.py
psd2html/rw.py
psd2html/storage.py
psd2html/utils.py
psd2html/builder/__init__.py
psd2html/builder/core.py
psd2html/builder/template.py
psd2html/builder/res/boilerplate.txt
psd2html/converter/Image.py
psd2html/converter/Layer.py
psd2html/converter/Type.py
psd2html/converter/__init__.py
psd2html/converter/core.py
psd2html/converter/utils.py
psd2html-0.3.0.dist-info/METADATA
psd2html-0.3.0.dist-info/WHEEL
psd2html-0.3.0.dist-info/entry_points.txt
psd2html-0.3.0.dist-info/top_level.txt
psd2html-0.3.0.dist-info/RECORD
