Metadata-Version: 2.1
Name: psd2html
Version: 0.3.0
Summary: Convert PSD file to HTML
Home-page: https://github.com/kimngei/psd2html
Author: Andrew Ngei
Author-email: andrew@kimngei.pro
License: MIT
Platform: UNKNOWN
Classifier: License :: OSI Approved :: MIT License
Classifier: Programming Language :: Python :: 3
Classifier: Programming Language :: Python :: 3.1
Classifier: Programming Language :: Python :: 3.2
Classifier: Programming Language :: Python :: 3.3
Classifier: Programming Language :: Python :: 3.4
Classifier: Programming Language :: Python :: 3.5
Classifier: Programming Language :: Python :: 3.6
Classifier: Programming Language :: Python :: 3.7
Requires-Python: >=3
Requires-Dist: psd-tools
Requires-Dist: lxml
Requires-Dist: beautifulsoup4
